{"bio":"Leshrac, Tormented Soul, is an entity torn from the heart of nature, a liminal being that exists half in one plane of existence, half in another. His penetrating intelligence is such that he can never ignore for a moment the agonizing horror at the heart of all creation. Once a great philosopher who sought the meaning of existence, he plumbed the depths of nature with the haunted Chronoptic Crystals, and was forever altered by the hideous mysteries thereby revealed to him. Now the darkest depths of his enlightenment are illumined only by the fitful glare of his arrogance. Like other elemental characters, he is completely at one with nature, but in his case it is a nature lurid and vile. He alone sees the evil truth of reality, and has no use for those who believe the cosmos reserves a special reward for those who practice benevolence.","bio_l":"拉席克，受折磨的灵魂，是一个从人性之中被撕裂出来的存在，他身体的一半存在于物质面，另外一半存在于非物质面。他敏锐的智慧使他能觉察到任何生物心中的最细微的恐惧。作为一个曾经毕生寻求存在意义的伟大哲学家，他用时光水晶探视了人性的最深处，在那里，他被展示在他面前的神秘的丑恶永远地改变了。傲慢与自负点燃了他内心最黑暗的深渊。和其他元素生命一样，他也是个完全随天性而行的人，但他的天性中只有邪恶和恐怖。他是唯一一个看到现实世界邪恶真理的存在，对那些相信上苍会对善举做出回馈的人，拉席克无疑是最大的反面例子。","stats":"<img src=\"Int\" alt=\"Intelligence\" />Intelligence:26 + 3.00<br /><img src=\"Agi\" alt=\"Agility\" />Agility:23 + 1.70<br /><img src=\"Str\" alt=\"Strength\" />Strength:16 + 1.50<br /><img src=\"Attack\" alt=\"Damage\" />Damage:19 - 23<br /><img src=\"Speed\" alt=\"Movespeed\" />Movespeed:315<br /><img src=\"Defense\" alt=\"Armor\" />Armor:3.22","detailstats":"\r\n\t\t\t\t\t\t<div class=\"redboxContent\">\r\n\t\t\t\t\t\t\t<div class=\"redboxTop\"></div>\r\n\t\t\t\t\t\t\t\t<div id=\"statsInner\">\r\n\t\t\t\t\t\t\t\t\t<div id=\"statsLeft\">\r\n\t\t\t\t\t\t\t\t\t\t<div class=\"statRow\">\r\n                                            <div class=\"statRowCol\">25</div>\r\n                                            <div class=\"statRowCol\">15</div>\r\n                                            <div class=\"statRowCol\">1</div>\r\n                                            Level\r\n                                        </div>\r\n\t\t\t\t\t\t\t\t\t\t<div class=\"statRowB\">\r\n                                            <div class=\"statRowColW\">1,518</div>\r\n                                            <div class=\"statRowColW\">853</div>\r\n                                            <div class=\"statRowColW\">454</div>\r\n                                            Hit Points\r\n                                        </div>\r\n\t\t\t\t\t\t\t\t\t\t<div class=\"statRow\">\r\n                                            <div class=\"statRowColW\">1,534</div>\r\n                                            <div class=\"statRowColW\">884</div>\r\n                                            <div class=\"statRowColW\">338</div>\r\n                                            Mana\r\n                                        </div>\r\n\t\t\t\t\t\t\t\t\t\t<div class=\"statRowB\">\r\n                                            <div class=\"statRowColW\">137-141</div>\r\n                                            <div class=\"statRowColW\">87-91</div>\r\n                                            <div class=\"statRowColW\">45-49</div>\r\n                                            Damage\r\n                                        </div>\r\n\t\t\t\t\t\t\t\t\t\t<div class=\"statRow\">\r\n                                            <div class=\"statRowColW\">12</div>\r\n                                            <div class=\"statRowColW\">7</div>\r\n                                            <div class=\"statRowColW\">3</div>\r\n                                            Armor\r\n                                        </div>\r\n\t\t\t\t\t\t\t\t\t</div>\r\n\t\t\t\t\t\t\t\t\t<div id=\"statsRight\">\r\n\t\t\t\t\t\t\t\t\t\t<div class=\"statRow\">&nbsp;</div>\r\n\t\t\t\t\t\t\t\t\t\t<div class=\"statRowB\">\r\n                                            <div class=\"statRowCol2W\">1800 / 900</div>\r\n                                            Sight Range\r\n                                        </div>\r\n\t\t\t\t\t\t\t\t\t\t<div class=\"statRow\">\r\n                                            <div class=\"statRowCol2W\">600</div>\r\n                                            Attack Range\r\n                                        </div>\r\n\t\t\t\t\t\t\t\t\t\t<div class=\"statRowB\">\r\n                                            <div class=\"statRowCol2W\">900</div>\r\n                                            Missile Speed\r\n                                        </div>\r\n\t\t\t\t\t\t\t\t\t</div>\r\n\t\t\t\t\t\t\t\t\t<br clear=\"both\" />\r\n\t\t\t\t\t\t\t\t</div>\r\n\t\t\t\t\t\t\t<div class=\"redboxBottom\"></div>\r\n\t\t\t\t\t\t</div>\r\n\t\t\t\t\t","detailstats1":[["Hit Points","1,518","853","454"],["Mana","1,534","884","338"],["Damage","137-141","87-91","45-49"],["Armor","12","7","3"]],"detailstats2":[["Sight Range","1800 / 900"],["Attack Range","600"],["Missile Speed","900"]],"abilities":[{"key_name":"leshrac_split_earth","dname":"撕裂大地","affects":"技能： <span class=\"attribVal\">点目标</span><br />影响： <span class=\"attribVal\">敌方单位</span><br />伤害类型： <span class=\"attribVal\">魔法</span>","desc":"撕裂敌人脚下的大地。造成伤害和短暂的眩晕。","dmg":"伤害类型： <span class=\"attribVal\">120 / 180 / 240 / 300</span>","attrib":"眩晕延迟: <span class=\"attribVal\">0.35</span><br />\n作用范围： <span class=\"attribVal\">150 / 175 / 200 / 225</span><br />\n眩晕时间： <span class=\"attribVal\">2</span>","cmb":"<img src=\"mana\" alt=\"魔法消耗\" />魔法消耗:100/125/140/160<br /><img src=\"cooldown\" alt=\"冷却时间\" />冷却时间:9","lore":"拉席克用他恶毒的意志扭曲大自然，撕裂大地摧毁那些挡他路的倒霉蛋。","hurl":"Leshrac"},{"key_name":"leshrac_diabolic_edict","dname":"恶魔赦令","affects":"技能： <span class=\"attribVal\">无目标</span><br />影响： <span class=\"attribVal\">敌方单位</span><br />伤害类型： <span class=\"attribVal\">混合</span>","desc":"使拉席克周围的区域充满魔法爆炸，对敌方单位和建筑造成混合伤害。范围内的敌人越少，他们受到的伤害就越大。持续8秒。","dmg":"伤害类型： <span class=\"attribVal\">12.5 / 25 / 37.5 / 50</span>","attrib":"爆炸次数: <span class=\"attribVal\">32</span><br />\n作用范围： <span class=\"attribVal\">500</span>","cmb":"<img src=\"mana\" alt=\"魔法消耗\" />魔法消耗:95/120/135/155<br /><img src=\"cooldown\" alt=\"冷却时间\" />冷却时间:22","lore":"古老的能量从一个位面向另一个位面爆发，将触碰到的一切化为灰烬。","hurl":"Leshrac"},{"key_name":"leshrac_lightning_storm","dname":"闪电风暴","affects":"技能： <span class=\"attribVal\">单位目标</span><br />影响： <span class=\"attribVal\">敌方单位</span><br />伤害类型： <span class=\"attribVal\">魔法</span>","desc":"召唤一片闪电风暴攻击目标敌方单位，并跳跃到附近的敌方单位。","dmg":"伤害类型： <span class=\"attribVal\">80 / 145 / 205 / 265</span>","attrib":"跳跃次数： <span class=\"attribVal\">4 / 6 / 7 / 8</span>","cmb":"<img src=\"mana\" alt=\"魔法消耗\" />魔法消耗:100/115/130/145<br /><img src=\"cooldown\" alt=\"冷却时间\" />冷却时间:5.50","lore":"受折磨的灵魂用来击倒敌人的闪电风暴展示了他对元素的精通。","hurl":"Leshrac"},{"key_name":"leshrac_pulse_nova","dname":"脉冲新星","affects":"技能： <span class=\"attribVal\">无目标, 切换</span><br />影响： <span class=\"attribVal\">敌方单位</span><br />伤害类型： <span class=\"attribVal\">魔法</span>","desc":"拉席克在他周围创造破坏性的能量波，每秒对附近敌方单位造成伤害。\r\n\r\n可用神杖升级。","dmg":"","attrib":"魔法消耗/每秒： <span class=\"attribVal\">20 / 40 / 60</span><br />\n作用范围： <span class=\"attribVal\">450</span><br />\n伤害： <span class=\"attribVal\">66 / 100 / 144</span><br />\n<span class=\"scepterVal\">神杖升级伤害：</span> <span class=\"attribVal\">88 / 133 / 177</span>","cmb":"<img src=\"mana\" alt=\"魔法消耗\" />魔法消耗:110/110/110<br /><img src=\"cooldown\" alt=\"冷却时间\" />冷却时间:1","lore":"必要时，受折磨的灵魂能操纵时空本身，毁灭弱小的存在。","hurl":"Leshrac"}],"itembuilds":{"Starting":["tango","clarity","clarity","flask","gauntlets","courier"],"Early":["magic_stick","boots","bracer","ward_observer"],"Core":["magic_wand","phase_boots","bloodstone"],"Luxury":["bloodstone","black_king_bar","sheepstick","ultimate_scepter","blink","shivas_guard","flying_courier"]},"hp":"intelligence","faction":"dire","name":"Leshrac","name_l":"拉席克","atk":"ranged","atk_l":"远程","roles":["Nuker","Pusher","Disabler","Support"],"roles_l":["爆发","推进","控制","辅助"]}