{"bio":"Storm Spirit is literally a force of nature--the wild power of wind and weather, bottled in human form. And a boisterous, jovial, irrepressible form it is! As jolly as a favorite uncle, he injects every scene with crackling energy. But it was not always thus, and there was tragedy in his creation. Generations ago, in the plains beyond the Wailing Mountains, a good people lay starving in drought and famine. A simple elementalist, Thunderkeg by name, used a forbidden spell to summon the spirit of the storm, asking for rain. Enraged at this mortal's presumption, the Storm Celestial known as Raijin lay waste to the land, scouring it bare with winds and flood. Thunderkeg was no match for the Celestial--at least until he cast a suicidal spell that forged their fates into one: he captured the Celestial in the cage of his own body. Trapped together, Thunderkeg's boundless good humor fused with Raijin's crazed energy, creating the jovial Raijin Thunderkeg, a Celestial who walks the world in physical form. ","bio_l":"风暴之灵，正如其名，是狂风和暴雨的野性凝成人形的自然之力。他狂放，乐天，恣意挥洒！就像个受人喜爱的大叔一样，他给所到之处充满欢乐的能量。但事实上，创造出他的是一起灾难。几个世代前，在悲叹山脉远处的平原上，很多人正因干旱和饥荒而挨饿。一个名叫风暴烈酒的元素使，使用禁忌的咒语召唤了风暴之灵，天真的向他祈求雨水。被称为雷神的暴风雨天神对这个凡人的放肆感到愤怒，打算用狂风和洪水把这片土地化为荒地。风暴烈酒完全不是天神的对手，直到最后他用了一个自杀性的咒语，将他和雷神的命运融在了一起，他用自己的身体作为牢笼捕获了雷神。被困在一起后，风暴烈酒那无限的幽默感与雷神疯狂的能量融合了，创造了乐天的雷神·风暴烈酒，一个以物质形态行于世间的天神。","stats":"<img src=\"Int\" alt=\"Intelligence\" />Intelligence:23 + 2.60<br /><img src=\"Agi\" alt=\"Agility\" />Agility:22 + 1.80<br /><img src=\"Str\" alt=\"Strength\" />Strength:19 + 1.50<br /><img src=\"Attack\" alt=\"Damage\" />Damage:22 - 32<br /><img src=\"Speed\" alt=\"Movespeed\" />Movespeed:290<br /><img src=\"Defense\" alt=\"Armor\" />Armor:5.08","stats1":[["Int","Intelligence","23 + 2.60"],["Agi","Agility","22 + 1.80"],["Str","Strength","19 + 1.50"],["Attack","Damage","22 - 32"],["Speed","Movespeed","290"],["Defense","Armor","5.08"]],"detailstats":"<div class=\"redboxContent\"><div class=\"redboxTop\"></div><div id=\"statsInner\"><div id=\"statsLeft\"><div class=\"statRow\"><div class=\"statRowCol\">25</div><div class=\"statRowCol\">15</div><div class=\"statRowCol\">1</div>等级</div><div class=\"statRowB\"><div class=\"statRowColW\">1,575</div><div class=\"statRowColW\">910</div><div class=\"statRowColW\">511</div>生命值</div><div class=\"statRow\"><div class=\"statRowColW\">1,370</div><div class=\"statRowColW\">772</div><div class=\"statRowColW\">299</div>魔法值</div><div class=\"statRowB\"><div class=\"statRowColW\">127-137</div><div class=\"statRowColW\">81-91</div><div class=\"statRowColW\">45-55</div>攻击力</div><div class=\"statRow\"><div class=\"statRowColW\">14</div><div class=\"statRowColW\">9</div><div class=\"statRowColW\">5</div>护甲</div></div><div id=\"statsRight\"><div class=\"statRow\"></div><div class=\"statRowB\"><div class=\"statRowCol2W\">1800 / 800</div>视野范围</div><div class=\"statRow\"><div class=\"statRowCol2W\">480</div>攻击范围</div><div class=\"statRowB\"><div class=\"statRowCol2W\">1100</div>弹道速度</div></div><br clear=\"both\" /></div><div class=\"redboxBottom\"></div></div>","detailstats1":[["生命值","1,575","910","511"],["魔法值","1,370","772","299"],["攻击力","127-137","81-91","45-55"],["护甲","14","9","5"]],"detailstats2":[["视野范围","1800 / 800"],["攻击范围","480"],["弹道速度","1100"]],"abilities":[{"key_name":"storm_spirit_static_remnant","dname":"残影","affects":"技能：<span class=\"attribVal\">无目标</span><br />伤害类型：<span class=\"attribVal\">魔法</span>","desc":"风暴之灵制造一个充满爆炸性能量的自身残影，如果有人接近就会引爆造成伤害，残影持续12秒。","dmg":"","notes":"残影在技能施放1秒后才能实体化。<br />残影在持续时间内拥有高空视野。<br />残影爆炸将伤害260码作用范围内的单位，但是触发范围是235码。","attrib":"作用范围： <span class=\"attribVal\">260</span><br />\n伤害： <span class=\"attribVal\">140 / 180 / 220 / 260</span>","cmb":"<img src=\"mana\" alt=\"魔法消耗\" />魔法消耗:70/80/90/100<br /><img src=\"cooldown\" alt=\"冷却时间\" />冷却时间:3.50","lore":"雷神·风暴烈酒的二象性让他可以欣赏自己被电时的百态。","hurl":"Storm_Spirit"},{"key_name":"storm_spirit_electric_vortex","dname":"电子涡流","affects":"技能：<span class=\"attribVal\">单位目标</span><br />影响：<span class=\"attribVal\">敌方单位</span>","desc":"将一个敌人拖到风暴之灵所在位置的涡流，同时也会降低风暴之灵自己50%的移动速度3秒。","dmg":"","notes":"","attrib":"持续时间： <span class=\"attribVal\">1 / 1.5 / 2 / 2.5</span>","cmb":"<img src=\"mana\" alt=\"魔法消耗\" />魔法消耗:100/110/120/130<br /><img src=\"cooldown\" alt=\"冷却时间\" />冷却时间:21/20/19/18","lore":"雷神狂暴的雷霆力量总是让其他人为之一电。","hurl":"Storm_Spirit"},{"key_name":"storm_spirit_overload","dname":"超负荷","affects":"技能：<span class=\"attribVal\">被动</span><br />伤害类型：<span class=\"attribVal\">魔法</span>","desc":"施法时会产生电荷，在风暴之灵下次攻击时被释放，对附近敌人造成伤害并减速。","dmg":"伤害类型：<span class=\"attribVal\">30 / 50 / 70 / 90</span>","notes":"使用物品不会触发超负荷。","attrib":"移动减速： <span class=\"attribVal\">80%</span><br />\n攻击速度降低： <span class=\"attribVal\">50</span><br />\n持续时间： <span class=\"attribVal\">0.6 / 0.6 / 0.6 / 0.6</span>","cmb":"","lore":"啪！嘶！咝！","hurl":"Storm_Spirit"},{"key_name":"storm_spirit_ball_lightning","dname":"球状闪电","affects":"技能：<span class=\"attribVal\">点目标</span><br />伤害类型：<span class=\"attribVal\">魔法</span>","desc":"风暴之灵变成不稳定的电流在战场上横冲直撞，直到他的魔法耗尽或到达目标才停下。每级提升伤害、速度和效果范围，施法消耗为15+7%的总魔法量，每移动100距离消耗总魔法量的10+1%，本技能造成的伤害每飞行100距离就会递增。","dmg":"伤害类型：<span class=\"attribVal\">8 / 12 / 16</span>","notes":"行进过程中可以使用瞬发技能。<br />该技能可以摧毁树木。<br />风暴之灵在球状闪电期间是无敌状态。","attrib":"速度： <span class=\"attribVal\">1250 / 1875 / 2500</span><br />\n作用范围： <span class=\"attribVal\">125 / 200 / 275</span><br />\n距离魔法消耗： <span class=\"attribVal\">0.7%</span>","cmb":"<img src=\"mana\" alt=\"魔法消耗\" />魔法消耗:15/15/15/15","lore":"风暴来袭。","hurl":"Storm_Spirit"}],"itembuilds":{"Starting":["tango","flask","clarity","mantle","circlet"],"Early":["magic_stick","boots","null_talisman","null_talisman"],"Core":["magic_wand","power_treads","orchid","bottle","tpscroll"],"Luxury":["sheepstick","bloodstone","sphere","black_king_bar","dagon","shivas_guard"]},"skillup":[{"groupName":"蓝猫主残影加点","desc":"1.残影R是一个4秒cd的AOE技能，相当不错的打钱技能<br />2.电子涡流E是一个2.5秒的控制及位移技能<br />3.超负荷V是一个被动加攻及范围减速的优秀被动技<br />4.大招球状闪电是一个0cd的blink技能，同时能造成相当可观的aoe伤害，蓝猫真正的核心技能。<br />蓝猫的加点方式非常灵活，全dota少数三个技能都能做为主升技能的英雄。完全可以根据阵容及个人喜好来决定加点方式，没有固定的套路，但有一个原则是要注意的，无论什么加点蓝猫4级时每个技能都需要至少1级，以保证前期一定的爆发力。<br />主残影的加点：偏AOE的打法，蓝猫的初期打钱能力会强很多，魔耗也相对较多。前期1级的v就能保证80%的减速效果，7级后满电子涡流可以让蓝猫的控制力更上一个台阶。","abilityKeys":["storm_spirit_static_remnant","storm_spirit_overload","storm_spirit_static_remnant","storm_spirit_electric_vortex","storm_spirit_static_remnant","storm_spirit_ball_lightning","storm_spirit_static_remnant","storm_spirit_electric_vortex","storm_spirit_electric_vortex","storm_spirit_electric_vortex","storm_spirit_ball_lightning","storm_spirit_overload","storm_spirit_overload","storm_spirit_overload","attribute_bonus","storm_spirit_ball_lightning","attribute_bonus","attribute_bonus","attribute_bonus","attribute_bonus","attribute_bonus","attribute_bonus","attribute_bonus","attribute_bonus","attribute_bonus"]},{"groupName":"蓝猫主电子涡流加点","desc":"主电子涡流的加点：偏控制的打法，初期配合有stun的英雄一路，压制能力更为突出。","abilityKeys":["storm_spirit_static_remnant","storm_spirit_overload","storm_spirit_electric_vortex","storm_spirit_electric_vortex","storm_spirit_electric_vortex","storm_spirit_ball_lightning","storm_spirit_electric_vortex","storm_spirit_static_remnant","storm_spirit_static_remnant","storm_spirit_static_remnant","storm_spirit_ball_lightning","storm_spirit_overload","storm_spirit_overload","storm_spirit_overload","attribute_bonus","storm_spirit_ball_lightning","attribute_bonus","attribute_bonus","attribute_bonus","attribute_bonus","attribute_bonus","attribute_bonus","attribute_bonus","attribute_bonus","attribute_bonus"]},{"groupName":"蓝猫推荐加点","desc":"<p>前期两级的被动让你对线更强势，7级时候3级E保证能完美连接R的伤害，之后把被动点满，多用大招和R触发被动输出。</p>","abilityKeys":["storm_spirit_static_remnant","storm_spirit_overload","storm_spirit_overload","storm_spirit_electric_vortex","storm_spirit_electric_vortex","storm_spirit_ball_lightning","storm_spirit_electric_vortex","storm_spirit_overload","storm_spirit_overload","storm_spirit_electric_vortex","storm_spirit_ball_lightning","storm_spirit_static_remnant","storm_spirit_static_remnant","storm_spirit_static_remnant","attribute_bonus","storm_spirit_ball_lightning","attribute_bonus","attribute_bonus","attribute_bonus","attribute_bonus","attribute_bonus","attribute_bonus","attribute_bonus","attribute_bonus","attribute_bonus"]}],"hp":"intelligence","faction":"radiant","name":"Storm Spirit","name_l":"风暴之灵","atk":"ranged","atk_l":"远程","roles":["Carry","Initiator","Escape","Disabler"],"roles_l":["核心","先手","逃生","控制"],"nickname_l":["Storm","Storm Spirit","蓝猫"],"statsall":{"init_str":19.0,"init_agi":22.0,"init_int":23.0,"lv_str":1.5,"lv_agi":1.8,"lv_int":2.6,"init_hp":511.0,"init_mp":299.0,"init_armor":5.08,"lv_hp":19.0,"lv_mp":13.0,"lv_armor":0.14,"init_min_dmg":22.0,"init_max_dmg":32.0,"lv_dmg":2.6}}